pulumi_docker/__init__.py
pulumi_docker/_enums.py
pulumi_docker/_inputs.py
pulumi_docker/_utilities.py
pulumi_docker/buildx_builder.py
pulumi_docker/container.py
pulumi_docker/get_logs.py
pulumi_docker/get_network.py
pulumi_docker/get_plugin.py
pulumi_docker/get_registry_image.py
pulumi_docker/get_registry_image_manifests.py
pulumi_docker/get_remote_image.py
pulumi_docker/image.py
pulumi_docker/network.py
pulumi_docker/outputs.py
pulumi_docker/plugin.py
pulumi_docker/provider.py
pulumi_docker/pulumi-plugin.json
pulumi_docker/py.typed
pulumi_docker/registry_image.py
pulumi_docker/remote_image.py
pulumi_docker/secret.py
pulumi_docker/service.py
pulumi_docker/service_config.py
pulumi_docker/tag.py
pulumi_docker/volume.py
pulumi_docker/config/__init__.py
pulumi_docker/config/__init__.pyi
pulumi_docker/config/outputs.py
pulumi_docker/config/vars.py
pulumi_docker-4.11.0.dist-info/METADATA
pulumi_docker-4.11.0.dist-info/WHEEL
pulumi_docker-4.11.0.dist-info/top_level.txt
pulumi_docker-4.11.0.dist-info/RECORD
